[
    {
        "id": "music_kit-3",
        "name": "音樂包 | Daniel Sadowski, Crimson Assault",
        "description": "遊戲音樂作曲家 Daniel Sadowski 為音樂包創作了狂熱旋律，既前衛又激昂，讓人激奮不已。",
        "rarity": {
            "id": "rarity_rare",
            "name": "高級"
        },
        "exclusive": false,
        "image": "https://steamcdn-a.akamaihd.net/apps/730/icons/econ/music_kits/danielsadowski_01.a2bf9e2640ea2dbbf5d0179b7669e09f5e7a7408.png"
    },
    {
        "id": "music_kit-4",
        "name": "音樂包 | Noisia, Sharpened",
        "description": "荷蘭電子樂三人組 Noisia 帶來的音樂強悍有電影感，以獨特的方式融合了傳統與創新。",
        "rarity": {
            "id": "rarity_rare",
            "name": "高級"
        },
        "exclusive": false,
        "image": "https://steamcdn-a.akamaihd.net/apps/730/icons/econ/music_kits/noisia_01.fe525cc5e29525708f4dc07c0a986a110075f796.png"
    },
    {
        "id": "music_kit-5",
        "name": "音樂包 | Robert Allaire, Insurgency",
        "description": "用音樂碾碎您的敵人。讓他們因獲獎作曲家 Robert Allaire 比你先走一步吧。",
        "rarity": {
            "id": "rarity_rare",
            "name": "高級"
        },
        "exclusive": false,
        "image": "https://steamcdn-a.akamaihd.net/apps/730/icons/econ/music_kits/robertallaire_01.61aafd2711f5f4ad260390f546fea72d57929900.png"
    },
    {
        "id": "music_kit-6",
        "name": "音樂包 | Sean Murray, A*D*8",
        "description": "由世上最大兩款戰爭遊戲的作曲家，以音波武裝將您的敵人送入地獄之門！！",
        "rarity": {
            "id": "rarity_rare",
            "name": "高級"
        },
        "exclusive": false,
        "image": "https://steamcdn-a.akamaihd.net/apps/730/icons/econ/music_kits/seanmurray_01.5e8de73cba9c875085372f52f70cbc3404e6dcc1.png"
    },
    {
        "id": "music_kit-7",
        "name": "音樂包 | Feed Me, High Noon",
        "description": "知名電子音樂人 Feed Me 所呈現的是現代電子空間中的西部拓荒大秀。",
        "rarity": {
            "id": "rarity_rare",
            "name": "高級"
        },
        "exclusive": false,
        "image": "https://steamcdn-a.akamaihd.net/apps/730/icons/econ/music_kits/feedme_01.8fcf645e3b3b2754bd9c478d1576b20cb3c18fa6.png"
    },
    {
        "id": "music_kit-8",
        "name": "音樂包 | Dren, Death's Head Demolition",
        "description": "由遊戲音樂作曲家 Dren 製作，這電影超級英雄金屬風的音樂包將使菜雞蛻變成大殺器！",
        "rarity": {
            "id": "rarity_rare",
            "name": "高級"
        },
        "exclusive": false,
        "image": "https://steamcdn-a.akamaihd.net/apps/730/icons/econ/music_kits/dren_01.fc2175fa289bd9953dcc7d6c672a75d9e42f6093.png"
    },
    {
        "id": "music_kit-9",
        "name": "音樂包 | Austin Wintory, Desert Fire",
        "description": "獲葛萊美獎提名的遊戲配樂作曲人 Austin Wintory 提問了，如果能用一個致命的瘋狂探戈把敵人引誘過來，又何必那麼麻煩的追著他們跑？",
        "rarity": {
            "id": "rarity_rare",
            "name": "高級"
        },
        "exclusive": false,
        "image": "https://steamcdn-a.akamaihd.net/apps/730/icons/econ/music_kits/austinwintory_01.5e3be7d7bd2e123d76969e7d17617545804a6c6b.png"
    },
    {
        "id": "music_kit-10",
        "name": "音樂包 | Sasha, LNOE",
        "description": "讓自己沉浸在這支電影般的原聲帶中，滿滿的飛揚弦樂、動人旋律還有鼓聲震動，全都出自舉世知名的 DJ 兼製作人 Sasha 之手。",
        "rarity": {
            "id": "rarity_rare",
            "name": "高級"
        },
        "exclusive": false,
        "image": "https://steamcdn-a.akamaihd.net/apps/730/icons/econ/music_kits/sasha_01.8ad1c2aebd178df3dff09c4f190b7064d46d142e.png"
    },
    {
        "id": "music_kit-11",
        "name": "音樂包 | Skog, Metal",
        "description": "讓金屬樂創作者 Skog 教教您什麼才是煞氣。",
        "rarity": {
            "id": "rarity_rare",
            "name": "高級"
        },
        "exclusive": false,
        "image": "https://steamcdn-a.akamaihd.net/apps/730/icons/econ/music_kits/skog_01.4869cd4270b65135eff75d121012db094bbf4973.png"
    },
    {
        "id": "music_kit-12",
        "name": "音樂包 | Midnight Riders, All I Want for Christmas",
        "description": "「佳節快樂，**蛋們！」\\n  -Midnight Riders",
        "rarity": {
            "id": "rarity_rare",
            "name": "高級"
        },
        "exclusive": false,
        "image": "https://steamcdn-a.akamaihd.net/apps/730/icons/econ/music_kits/midnightriders_01.22ad94b80a058ad3cb1373fcf0f69e6983491765.png"
    },
    {
        "id": "music_kit-13",
        "name": "音樂包 | Matt Lange, IsoRhythm",
        "description": "來場聽覺饗宴，這是一個具電影感、干擾氛圍和強力搏動韻律的組曲，由電子樂製作人兼創新人士 Matt Lange 製做。",
        "rarity": {
            "id": "rarity_rare",
            "name": "高級"
        },
        "exclusive": false,
        "image": "https://steamcdn-a.akamaihd.net/apps/730/icons/econ/music_kits/mattlange_01.a5321f2db9fd84c93e384e28d6048784913af83a.png"
    },
    {
        "id": "music_kit-14",
        "name": "音樂包 | Mateo Messina, For No Mankind",
        "description": "玩弄敵人於掌心。由葛萊美得獎作曲家 Mateo Messina 獻上的純粹震撼力。",
        "rarity": {
            "id": "rarity_rare",
            "name": "高級"
        },
        "exclusive": false,
        "image": "https://steamcdn-a.akamaihd.net/apps/730/icons/econ/music_kits/mateomessina_01.94e787b3d227841ea7a3cd48dfb911131a1bb1ef.png"
    },
    {
        "id": "music_kit-15",
        "name": "音樂包 | Various Artists, Hotline Miami",
        "description": "由風格各異的電子音樂人共同出手，在指標性遊戲《Hotline Miami》這個振奮人心的音樂包中帶來殘暴的節奏打擊。",
        "rarity": {
            "id": "rarity_rare",
            "name": "高級"
        },
        "exclusive": false,
        "image": "https://steamcdn-a.akamaihd.net/apps/730/icons/econ/music_kits/hotlinemiami_01.df89086218adcaf00b86cffff78191f2f5bcb500.png"
    },
    {
        "id": "music_kit-16",
        "name": "音樂包 | Daniel Sadowski, Total Domination",
        "description": "作曲家 Daniel Sadowski 把整個門檻都提高了，這組作品充滿激進的電子樂節奏、創意音效和一種令人興奮又有未來感的氛圍。「小心：腎上腺素即將飆高！」",
        "rarity": {
            "id": "rarity_rare",
            "name": "高級"
        },
        "exclusive": false,
        "image": "https://steamcdn-a.akamaihd.net/apps/730/icons/econ/music_kits/danielsadowski_02.5a250ef0a92cbe07b1fd5d26afd1fda52d10ee8d.png"
    },
    {
        "id": "music_kit-17",
        "name": "音樂包 | Damjan Mravunac, The Talos Principle",
        "description": "作曲家 Damjan Mravunac 所創作的音樂包混合了電影般的能量動感與史詩般的合唱於一身，擷取了 Croteam 出品、極富盛名的作品《The Talos Principle》的音樂精華。",
        "rarity": {
            "id": "rarity_rare",
            "name": "高級"
        },
        "exclusive": false,
        "image": "https://steamcdn-a.akamaihd.net/apps/730/icons/econ/music_kits/damjanmravunac_01.538b68f26daddde3c83f6ae44de9947ab7e8c2d0.png"
    },
    {
        "id": "music_kit-18",
        "name": "音樂包 | Proxy, Battlepack",
        "description": "俄式重度電音藝術家 PROXY 為絕對武力帶來了他自己獨特的重砲。合成武器音效與最精細的混音室技術交迸出的火花創造了這份獨一無二的音樂包。",
        "rarity": {
            "id": "rarity_rare",
            "name": "高級"
        },
        "exclusive": false,
        "image": "https://steamcdn-a.akamaihd.net/apps/730/icons/econ/music_kits/proxy_01.12796e09ff47c1dd25757cff0761bf7b880dfb3b.png"
    },
    {
        "id": "music_kit-19",
        "name": "音樂包 | Ki:Theory, MOLOTOV",
        "description": "錄音藝術家兼 Dota 第 4 屆國際錦標賽上的表演者 Ki:Theory 投下重磅巨彈！帶來這組燙手的銳利電子黑暗搖滾音樂包。",
        "rarity": {
            "id": "rarity_rare",
            "name": "高級"
        },
        "exclusive": false,
        "image": "https://steamcdn-a.akamaihd.net/apps/730/icons/econ/music_kits/kitheory_01.00e97bde40259873dfe52ffe809c0a05418d11ff.png"
    },
    {
        "id": "music_kit-20",
        "name": "音樂包 | Troels Folmann, Uber Blasto Phone",
        "description": "勝利號角般的樂聲結合現代性的脈動創造出這套炸裂全場的組曲，創作者為贏得無數獎項的得獎作曲家 Troels Folmann。",
        "rarity": {
            "id": "rarity_rare",
            "name": "高級"
        },
        "exclusive": false,
        "image": "https://steamcdn-a.akamaihd.net/apps/730/icons/econ/music_kits/troelsfolmann_01.62c19e1f4ed3c30ec238d088ddc036671e574972.png"
    },
    {
        "id": "music_kit-21",
        "name": "音樂包 | Kelly Bailey, Hazardous Environments",
        "description": "Kelly Bailey，Valve《戰慄時空》系列的作曲家，創作出一組了受《戰慄時空》宇宙的黑暗面啟發的全新末世風音樂。",
        "rarity": {
            "id": "rarity_rare",
            "name": "高級"
        },
        "exclusive": false,
        "image": "https://steamcdn-a.akamaihd.net/apps/730/icons/econ/music_kits/kellybailey_01.5f62031bbb9d6859db2f1f8a575a6dcd1079c928.png"
    },
    {
        "id": "music_kit-22",
        "name": "音樂包 | Skog, II-Headshot",
        "description": "金屬樂作曲家兼製作人 Jocke Skog 帶著全新的強力重擊金屬音樂包回歸。此組曲一出，其它 CS:GO 音樂包都成了可愛溫馨舒適小曲。現在就去贏得 MVP 讓每個人都聽見您有多厲害！",
        "rarity": {
            "id": "rarity_rare",
            "name": "高級"
        },
        "exclusive": false,
        "image": "https://steamcdn-a.akamaihd.net/apps/730/icons/econ/music_kits/skog_02.eeb9ddb340f8a0b530b097f6a7f37cd922334f53.png"
    },
    {
        "id": "music_kit-23",
        "name": "音樂包 | Daniel Sadowski, The 8-Bit Kit",
        "description": "Daniel Sadowski 使用純正的 8 位元音效為絕對武力創作了首個 8 位元音樂包。",
        "rarity": {
            "id": "rarity_rare",
            "name": "高級"
        },
        "exclusive": false,
        "image": "https://steamcdn-a.akamaihd.net/apps/730/icons/econ/music_kits/danielsadowski_03.23f670f86d302907e1965780bf0fc145ab334235.png"
    },
    {
        "id": "music_kit-24",
        "name": "音樂包 | AWOLNATION, I Am",
        "description": "AWOLNATION 另類搖滾樂團 AWOLNATION 為您帶來值得永久珍藏的音樂包。此音樂包收錄了多首曲風迥異的金曲，以及單曲\\\"I Am\\\"和多白金銷量的熱門歌曲\\\"Sail\\\"片段。",
        "rarity": {
            "id": "rarity_rare",
            "name": "高級"
        },
        "exclusive": false,
        "image": "https://steamcdn-a.akamaihd.net/apps/730/icons/econ/music_kits/awolnation_01.2ffc1650abdea909957237a616b8a85f8ca686e4.png"
    },
    {
        "id": "music_kit-25",
        "name": "音樂包 | Mord Fustang, Diamonds",
        "description": "鑽石恆久遠，一顆永流傳。投入 Mord Fustang 的快速電子琶音之中，享受這一組全新的律動與氛圍。",
        "rarity": {
            "id": "rarity_rare",
            "name": "高級"
        },
        "exclusive": false,
        "image": "https://steamcdn-a.akamaihd.net/apps/730/icons/econ/music_kits/mordfustang_01.19b15e98c183e4cf11f06ee9d59a890d91513a8b.png"
    },
    {
        "id": "music_kit-26",
        "name": "音樂包 | Michael Bross, Invasion!",
        "description": "Michael Bross 結合了史詩與電影在鐵克諾加頹廢搖滾的樂音之中，讓您在戰鬥中充滿身為狠角色的感受。",
        "rarity": {
            "id": "rarity_rare",
            "name": "高級"
        },
        "exclusive": false,
        "image": "https://steamcdn-a.akamaihd.net/apps/730/icons/econ/music_kits/michaelbross_01.adff3cdea10bca94a92025cc1fd052b5a2327a8d.png"
    },
    {
        "id": "music_kit-27",
        "name": "音樂包 | Ian Hultquist, Lion's Mouth",
        "description": "混合了讓人悸動的弦樂與合成樂，再加上隆隆的戰鼓聲，作曲家 Ian Hultquist 帶來的強有力原聲帶讓您準備好上戰場一較高下。",
        "rarity": {
            "id": "rarity_rare",
            "name": "高級"
        },
        "exclusive": false,
        "image": "https://steamcdn-a.akamaihd.net/apps/730/icons/econ/music_kits/ianhultquist_01.3157f761e847ba428bbf82fbfa7f07c792a5d626.png"
    },
    {
        "id": "music_kit-28",
        "name": "音樂包 | New Beat Fund, Sponge Fingerz",
        "description": "陽光衝浪搖滾加上嘻哈、龐克與車庫流行元素。放手一戰，爆頭擊殺。",
        "rarity": {
            "id": "rarity_rare",
            "name": "高級"
        },
        "exclusive": false,
        "image": "https://steamcdn-a.akamaihd.net/apps/730/icons/econ/music_kits/newbeatfund_01.f711bcd037c0ccc121b3ef4d0d45b7646ba3ccce.png"
    },
    {
        "id": "music_kit-29",
        "name": "音樂包 | Beartooth, Disgusting",
        "description": "Beartooth 帶來能讓觀眾燥動起來、氣勢洶洶的返璞歸真重硬核節奏。最適合在用 Scout 不用開鏡擊殺敵人時聆聽。盡情搖滾，至死方休！",
        "rarity": {
            "id": "rarity_rare",
            "name": "高級"
        },
        "exclusive": false,
        "image": "https://steamcdn-a.akamaihd.net/apps/730/icons/econ/music_kits/beartooth_01.7c8272a14a47916ceb4b59bc18b1f2d0036b5523.png"
    },
    {
        "id": "music_kit-30",
        "name": "音樂包 | Lennie Moore, Java Havana Funkaloo",
        "description": "遊戲作曲家 Lennie Moore 獻上一道芳香又辛辣的爵士放克。冷冷地聽也對味，正像被您火爆了結後的敵人屍體一樣。",
        "rarity": {
            "id": "rarity_rare",
            "name": "高級"
        },
        "exclusive": false,
        "image": "https://steamcdn-a.akamaihd.net/apps/730/icons/econ/music_kits/lenniemoore_01.85efce33bf5d30452a8e84e4a55c78c9b44775d3.png"
    },
    {
        "id": "music_kit-31",
        "name": "音樂包 | Darude, Moments CS:GO",
        "description": "放心屈服於充滿芬蘭創作者 Darude 音樂風味與格調的音景之中吧。 來自一位著名的舞曲先驅的音樂作品集，讓自己沈浸於具革新泛音及刺激旋律結構的重節奏混合音樂。",
        "rarity": {
            "id": "rarity_rare",
            "name": "高級"
        },
        "exclusive": false,
        "image": "https://steamcdn-a.akamaihd.net/apps/730/icons/econ/music_kits/darude_01.7c92a500270301ab6883f6a144f59cc28571521d.png"
    },
    {
        "id": "music_kit-32",
        "name": "音樂包 | Beartooth, Aggressive",
        "description": "Beartooth 再次回歸。這全新的音樂包比上回的節奏更強烈，更氣勢洶洶。而且我們再三加強了 MVP 主題曲的節奏，這樣您的對手在落敗的時候情緒便會更加低落。",
        "rarity": {
            "id": "rarity_rare",
            "name": "高級"
        },
        "exclusive": false,
        "image": "https://steamcdn-a.akamaihd.net/apps/730/icons/econ/music_kits/beartooth_02.6ec3c958567128d94455f7c3459b22ad2061a12c.png"
    },
    {
        "id": "music_kit-33",
        "name": "音樂包 | Blitz Kids, The Good Youth",
        "description": "英式搖滾 / 龐克樂團 Blitz Kids 為大家帶來能讓您在突擊 B 點的路上，回想起高中時期與好友深夜飆車美好時光的音樂包。飆速疾走與感受青春時這個音樂包再適合不過。",
        "rarity": {
            "id": "rarity_rare",
            "name": "高級"
        },
        "exclusive": false,
        "image": "https://steamcdn-a.akamaihd.net/apps/730/icons/econ/music_kits/blitzkids_01.5f0480468f7b46a838bb761dfdfa0788469e3e17.png"
    },
    {
        "id": "music_kit-34",
        "name": "音樂包 | Hundredth, FREE",
        "description": "Hundredth 以他們對旋律硬核獨特的見解把重金屬帶到這個世界。聽著這絕配的音樂逃離束縛（《Break Free》）或回到 Dust 炸爆那些不值一提的人吧。",
        "rarity": {
            "id": "rarity_rare",
            "name": "高級"
        },
        "exclusive": false,
        "image": "https://steamcdn-a.akamaihd.net/apps/730/icons/econ/music_kits/hundredth_01.f6032850a26e9b1fdc9e8435a574282b27792747.png"
    },
    {
        "id": "music_kit-35",
        "name": "音樂包 | Neck Deep, Life's Not Out To Get You",
        "description": "有時候就是要聽著流行龐克渡過艱苦的一天。不論是被蹲點狙擊手為難，還是被斷掉超高的連殺，Neck Deep 在此向大家證明人生並沒有故意要針對您（《Life's Not Out To Get You》），但敵方隊伍絕對有意。",
        "rarity": {
            "id": "rarity_rare",
            "name": "高級"
        },
        "exclusive": false,
        "image": "https://steamcdn-a.akamaihd.net/apps/730/icons/econ/music_kits/neckdeep_01.f2b26359736f263c519fb5bffbaf590c5cbdcd17.png"
    },
    {
        "id": "music_kit-36",
        "name": "音樂包 | Roam, Backbone",
        "description": "Roam 為大家帶來快節奏且直接了當的流行龐克，無論是觀眾還是玩家都會跟著音樂動起來。帶著這個音樂包突襲敵人，在對方還未搞清楚狀況之前將其隊伍殲滅，證明自己是個有「Backbone」（骨氣）的人吧。",
        "rarity": {
            "id": "rarity_rare",
            "name": "高級"
        },
        "exclusive": false,
        "image": "https://steamcdn-a.akamaihd.net/apps/730/icons/econ/music_kits/roam_01.de919629f1df756d298d81cdb24e658eacf7090c.png"
    },
    {
        "id": "music_kit-37",
        "name": "音樂包 | Twin Atlantic, GLA",
        "description": "Twin Atlantic 為 CS:GO 帶來比以往更重節奏、更喧鬧和更大聲的音樂，以蘇格蘭搖滾的火力助大家震懾敵人。",
        "rarity": {
            "id": "rarity_rare",
            "name": "高級"
        },
        "exclusive": false,
        "image": "https://steamcdn-a.akamaihd.net/apps/730/icons/econ/music_kits/twinatlantic_01.a3e60569d052721275943b7fa0a563e59dd2f105.png"
    },
    {
        "id": "music_kit-38",
        "name": "音樂包 | Skog, III-Arena",
        "description": "Skog 帶著第三部粉碎重金屬音樂包再次到來。這次的音樂添加了活潑的電子風，在大量的吉他重覆樂段中結合了同樣多的高潮樂段、循環元素以及持續音。",
        "rarity": {
            "id": "rarity_rare",
            "name": "高級"
        },
        "exclusive": false,
        "image": "https://steamcdn-a.akamaihd.net/apps/730/icons/econ/music_kits/skog_03.2a6b65fe2443cd27414c8ea48614c4b9386c377a.png"
    },
    {
        "id": "music_kit-39",
        "name": "音樂包 | The Verkkars, EZ4ENCE",
        "description": "The Verkkars 憑著這首向 ENCE 致敬的震撼心靈之作登上芬蘭音樂排行榜。真的有那麼 EZ 嗎？",
        "rarity": {
            "id": "rarity_rare",
            "name": "高級"
        },
        "exclusive": false,
        "image": "https://steamcdn-a.akamaihd.net/apps/730/icons/econ/music_kits/theverkkars_01.c76969d8c14a9a74c71f0d5efce6453f7b70bf43.png"
    },
    {
        "id": "music_kit-40",
        "name": "Halo - The Master Chief Collection",
        "description": "以由 Halo 宇宙中象徵性的音樂時刻組成的《Master Chief Collection》音樂包，為自己的絕對武力音訊體驗帶來傳奇改造。© 2019 343 Industries。版權所有。由 343 Industries 授權使用。《Halo: The Master Chief Collection》和 Halo 標誌均為 Microsoft 公司集團的商標。",
        "rarity": {
            "id": "rarity_rare",
            "name": "高級"
        },
        "exclusive": true,
        "image": "https://steamcdn-a.akamaihd.net/apps/730/icons/econ/music_kits/halo_01.a49952f4e059871c05f6d829f6f29a1a2ccbddc2.png"
    },
    {
        "id": "music_kit-41",
        "name": "音樂包 | Scarlxrd: King, Scar",
        "description": "Scarlxrd 將重陷阱拍子融入自己的表演風格，製造出屬於他獨特的音樂子流派。如他在現場表演此令人興奮的混合音樂總能抓住所有觀眾的注意力。",
        "rarity": {
            "id": "rarity_rare",
            "name": "高級"
        },
        "exclusive": false,
        "image": "https://steamcdn-a.akamaihd.net/apps/730/icons/econ/music_kits/scarlxrd_01.f1deaed73c132260c8354198bc2f23e939b139b3.png"
    },
    {
        "id": "music_kit-42",
        "name": "《戰慄時空：艾莉克絲》- 反公民",
        "description": "本音樂包旨在紀念 Valve 重返《戰慄時空》系列的 VR 大作：《戰慄時空：艾莉克絲》。 您是人類存活下去的最後一絲希望，您的沉浸式環境互動體驗也將在《絕對武力：全球攻勢》延續下去。",
        "rarity": {
            "id": "rarity_rare",
            "name": "高級"
        },
        "exclusive": true,
        "image": "https://steamcdn-a.akamaihd.net/apps/730/icons/econ/music_kits/hlalyx_01.695e0b07f37980650d408fd3260737df825d1f91.png"
    },
    {
        "id": "music_kit-43",
        "name": "音樂包 | Austin Wintory - Bachram",
        "description": "Austin Wintory 混合了賽爾提克神話與熱燒的電子樂，再加上大份量的 Peter Hollens 嗓音，調製了這份跨曲風的音樂包。",
        "rarity": {
            "id": "rarity_rare",
            "name": "高級"
        },
        "exclusive": false,
        "image": "https://steamcdn-a.akamaihd.net/apps/730/icons/econ/music_kits/austinwintory_02.c8fb789fab88586d69b2bc822332a7a86afb83ed.png"
    },
    {
        "id": "music_kit-44",
        "name": "音樂包 | Dren - Gunman Taco Truck",
        "description": "這組末世風墨西哥街頭樂原為熱門獨立遊戲《Gunman Taco Truck》的原聲帶，現在為 CS:GO 帶來墨西哥風味強烈的的曲調，包括 Pollo Diablo 還有 Persecución de Helltain！",
        "rarity": {
            "id": "rarity_rare",
            "name": "高級"
        },
        "exclusive": false,
        "image": "https://steamcdn-a.akamaihd.net/apps/730/icons/econ/music_kits/dren_02.63647ccdee069255f19589d7ce2d5b7de591aa6b.png"
    },
    {
        "id": "music_kit-45",
        "name": "音樂包 | Daniel Sadowski - Eye of the Dragon",
        "description": "曾為您帶來音樂包《Total Domination》、《The 8-Bit Kit》和《Crimson Assault》的作曲家 Daniel Sadowski 這回獻上《Eye Of The Dragon》。音樂人 Daniel Sadowski 混合了忍者、槍枝、嘻哈和鐵克諾，創造了一個動作緊湊的音樂包。<b>忍者最為人所知的是其快速精準的攻擊手法，而且敵人完全無法捉摸其行蹤。</b>",
        "rarity": {
            "id": "rarity_rare",
            "name": "高級"
        },
        "exclusive": false,
        "image": "https://steamcdn-a.akamaihd.net/apps/730/icons/econ/music_kits/danielsadowski_04.6be221622292eabfe4da40d166fa75a6d0dcec55.png"
    },
    {
        "id": "music_kit-46",
        "name": "音樂包 | Tree Adams 與 Ben Bromfield - M.U.D.D. FORCE",
        "description": "M.U.D.D. FORCE 由操縱強大混沌之力的煉金術士組成——作曲家 Tree Adams 和 Ben Bromfield 將史詩式戰鬥主題與嚴苛的合成器音效結合，煉成一股擁有巨大破壞力的漩渦。",
        "rarity": {
            "id": "rarity_rare",
            "name": "高級"
        },
        "exclusive": false,
        "image": "https://steamcdn-a.akamaihd.net/apps/730/icons/econ/music_kits/treeadams_benbromfield_01.08ca88c8f650b524f709a3e2e05e3160579771c3.png"
    },
    {
        "id": "music_kit-47",
        "name": "音樂包 | Tim Huling - Neo Noir",
        "description": "作曲家 Tim Huling 為大家帶來融合當代韻律與節拍的經典黑色電影風格樂曲。",
        "rarity": {
            "id": "rarity_rare",
            "name": "高級"
        },
        "exclusive": false,
        "image": "https://steamcdn-a.akamaihd.net/apps/730/icons/econ/music_kits/timhuling_01.518aa6b46cec0d809e1e984041c66fd00f22b005.png"
    },
    {
        "id": "music_kit-48",
        "name": "音樂包 | Sam Marshall - Bodacious",
        "description": "受 90 年代初的放克電子遊戲音樂啟發，作曲家 Sam Marshall 編寫了幾首有現代趣味的經典遊戲懷舊風樂曲。",
        "rarity": {
            "id": "rarity_rare",
            "name": "高級"
        },
        "exclusive": false,
        "image": "https://steamcdn-a.akamaihd.net/apps/730/icons/econ/music_kits/sammarshall_01.05adc292af4abcfe6cd6b2d76a6020ab80122ada.png"
    },
    {
        "id": "music_kit-49",
        "name": "音樂包 | Matt Levine - Drifter",
        "description": "作曲家 Matt Levine 以大搖大擺的曲風向義大利式西部片表示不加掩飾的敬意。「儘管動手，我求之不得…」聽著此音樂說出這話實在太爽了。",
        "rarity": {
            "id": "rarity_rare",
            "name": "高級"
        },
        "exclusive": false,
        "image": "https://steamcdn-a.akamaihd.net/apps/730/icons/econ/music_kits/mattlevine_01.974b450e606547a138e15a540597164bcd70a8e8.png"
    },
    {
        "id": "music_kit-50",
        "name": "音樂包 | Amon Tobin - All for Dust",
        "description": "傳奇製作人 Amon Tobin 這次透過真空管放大器將他獨特的音樂美學帶給 CS:GO。",
        "rarity": {
            "id": "rarity_rare",
            "name": "高級"
        },
        "exclusive": false,
        "image": "https://steamcdn-a.akamaihd.net/apps/730/icons/econ/music_kits/amontobin_01.2cf4f8b98a111fc847576bb6a8feb3364a2cfa1b.png"
    },
    {
        "id": "music_kit-51",
        "name": "Darren Kor -《Hades》音樂包",
        "description": "沒錯，時不時是會錯過扣下板機的時機，但絕對不容錯過的是這份令人熱血沸騰、出自 Supergiant 的類 Rogue 迷宮探索作品《Hades》中冥界的音樂包。",
        "rarity": {
            "id": "rarity_rare",
            "name": "高級"
        },
        "exclusive": true,
        "image": "https://steamcdn-a.akamaihd.net/apps/730/icons/econ/music_kits/hades_01.41336135661d422039fe700e0bf4c8176886194e.png"
    },
    {
        "id": "music_kit-52",
        "name": "音樂包 | Neck Deep，《The Lowlife》組合",
        "description": "以 Neck Deep 全新的音樂包，來證明自己並非凡夫俗子（比地圖上所有人優越），當中包含樂團專輯《All Distortions Are Intentional》中的曲目。",
        "rarity": {
            "id": "rarity_rare",
            "name": "高級"
        },
        "exclusive": false,
        "image": "https://steamcdn-a.akamaihd.net/apps/730/icons/econ/music_kits/neckdeep_02.d00e38b24d5ca285fd34411afc34b874ab80cd1b.png"
    },
    {
        "id": "music_kit-53",
        "name": "音樂包 | Scarlxrd，《CHAIN$AW.LXADXUT》",
        "description": "SCARLXRD 在 CHAIN$AW 中以粗獷的演唱配合拍子強烈的音樂，展現了前所未有的最佳狀態。",
        "rarity": {
            "id": "rarity_rare",
            "name": "高級"
        },
        "exclusive": false,
        "image": "https://steamcdn-a.akamaihd.net/apps/730/icons/econ/music_kits/scarlxrd_02.9d630d5c49841c359e6def0bc2e4e24b62b2f233.png"
    },
    {
        "id": "music_kit-54",
        "name": "音樂包 | Austin Wintory - Mocha Petal",
        "description": "Austin Wintory 解答了人類好奇很久的問題：如果將露天啤酒屋的手風琴波爾卡音樂與頹廢風的重金屬混在一起，會有什麼效果呢？",
        "rarity": {
            "id": "rarity_rare",
            "name": "高級"
        },
        "exclusive": false,
        "image": "https://steamcdn-a.akamaihd.net/apps/730/icons/econ/music_kits/austinwintory_03.18f6213b11eccdb12237547a78c2cb70fb54d829.png"
    },
    {
        "id": "music_kit-55",
        "name": "音樂包 | Chipzel - ~Yellow Magic~",
        "description": "身為遊戲音樂作曲家的晶片音樂傳奇人物 Chipzel，帶來了受充滿雜訊的「Speak & Spell」玩具語音所啟發，且充滿趣味、放克元素和風味的混合音樂。",
        "rarity": {
            "id": "rarity_rare",
            "name": "高級"
        },
        "exclusive": false,
        "image": "https://steamcdn-a.akamaihd.net/apps/730/icons/econ/music_kits/chipzel_01.5f4d9f5a440a9b66807b3a1ca40bfe61bddc483c.png"
    },
    {
        "id": "music_kit-56",
        "name": "音樂包 | Freaky DNA - Vici",
        "description": "歌劇、8 位元音效、類比合成器。有什麼可挑剔的嗎？晶片音樂專家 Freaky DNA 與女高音 Leanne Koch 合作，帶來強勁節奏和歡樂時光！",
        "rarity": {
            "id": "rarity_rare",
            "name": "高級"
        },
        "exclusive": false,
        "image": "https://steamcdn-a.akamaihd.net/apps/730/icons/econ/music_kits/freakydna_01.96afa403f5a9e023408e88496369361b4f557f44.png"
    },
    {
        "id": "music_kit-57",
        "name": "音樂包 | Jesse Harlin - Astro Bellum",
        "description": "受到 70 與 80 年代以及更新的經典科幻作品啟發，作曲家 Jesse Harlin 為大家帶來浮誇的外太空歌劇。",
        "rarity": {
            "id": "rarity_rare",
            "name": "高級"
        },
        "exclusive": false,
        "image": "https://steamcdn-a.akamaihd.net/apps/730/icons/econ/music_kits/jesseharlin_01.8698a32cdebbee16225c231bad5b422256a4dfe2.png"
    },
    {
        "id": "music_kit-58",
        "name": "音樂包 | Laura Shigihara - Work Hard, Play Hard",
        "description": "遊戲音樂作曲家和開發者 Laura Shigihara 會大聲又自豪地為您向全世界宣揚您是 MVP 的消息。希望您享受這融合了 90 年代舞曲、復古電子遊戲合成器和一點點《植物大戰殭屍》元素的獨特混合音樂。",
        "rarity": {
            "id": "rarity_rare",
            "name": "高級"
        },
        "exclusive": false,
        "image": "https://steamcdn-a.akamaihd.net/apps/730/icons/econ/music_kits/laurashigihara_01.6ccd2d1904530773115ba88c2cbb389d3da46df3.png"
    },
    {
        "id": "music_kit-59",
        "name": "音樂包 | Sarah Schachner - KOLIBRI",
        "description": "Sarah Schachner 為大家呈獻，由具有自我意識的北歐機械人組成的反烏托邦哥德搖滾合唱團，獻上音樂並帶出必須要毀滅人類的決定。",
        "rarity": {
            "id": "rarity_rare",
            "name": "高級"
        },
        "exclusive": false,
        "image": "https://steamcdn-a.akamaihd.net/apps/730/icons/econ/music_kits/sarahschachner_01.5a5bef300a44f8f54ba3d817245cb32f66d1c85f.png"
    },
    {
        "id": "music_kit-60",
        "name": "音樂包 | bbno$, u mad!",
        "description": "bbno$ 專為惡毒玩家打造的代表歌曲《u mad!》！你惱羞喔？笑死，多練練再來吧。研究顯示帶著這個音樂包進行遊戲，馬上就能從銀牌上地球。",
        "rarity": {
            "id": "rarity_rare",
            "name": "高級"
        },
        "exclusive": false,
        "image": "https://steamcdn-a.akamaihd.net/apps/730/icons/econ/music_kits/bbnos_01.41bea5be0ec1c11d2f9c58cc24d175ab62870b74.png"
    },
    {
        "id": "music_kit-61",
        "name": "音樂包 | The Verkkars & n0thing - Flashbang Dance",
        "description": "從陽光四射的加州到冰冷嚴寒的拉普蘭，由絕對武力傳奇選手 n0thing 聯合 The Verkkars 合力打造，帶來暢銷單曲《Flashbang Dance》！3，2，1，眼被亮瞎了！",
        "rarity": {
            "id": "rarity_rare",
            "name": "高級"
        },
        "exclusive": false,
        "image": "https://steamcdn-a.akamaihd.net/apps/730/icons/econ/music_kits/theverkkars_02.329034c68612e8f00f0f18e20d7a84f7d2b68627.png"
    },
    {
        "id": "music_kit-62",
        "name": "音樂包 | 3kliksphilip - Heading for the Source",
        "description": "在邁向職業選手的路上？還是無意中落入谷底？讓這音樂包中的 80 年代合成器音樂與夢幻的旋律帶大家回到過去，慢慢回想起昔日美好的時光。",
        "rarity": {
            "id": "rarity_rare",
            "name": "高級"
        },
        "exclusive": false,
        "image": "https://steamcdn-a.akamaihd.net/apps/730/icons/econ/music_kits/3kliksphilip_01.376011867dada400b17c357748d344c1491a2881.png"
    },
    {
        "id": "music_kit-63",
        "name": "音樂包 | Humanity's Last Breath - Void",
        "description": "瑞典樂團 Humanity's Last Breath 沉重有力地為大家帶來他們的 Void 音樂包。震撼的鼓聲和大量的重覆樂段，營造毛骨悚然的氛圍。",
        "rarity": {
            "id": "rarity_rare",
            "name": "高級"
        },
        "exclusive": false,
        "image": "https://steamcdn-a.akamaihd.net/apps/730/icons/econ/music_kits/hlb_01.0b08df9d78b230f26b9e7eb4f8dca11f298b30ef.png"
    },
    {
        "id": "music_kit-64",
        "name": "音樂包 | Juelz - Shooters",
        "description": "新陷阱風合成器、粗獷的 808 鼓機、史詩式的鋼琴重覆樂段再配上大量槍聲音效。這首來自 Juelz 的元老級陷阱代表歌曲《Shooters》造就了這款出類拔萃的音樂包，僅適合 MVP 玩家使用。",
        "rarity": {
            "id": "rarity_rare",
            "name": "高級"
        },
        "exclusive": false,
        "image": "https://steamcdn-a.akamaihd.net/apps/730/icons/econ/music_kits/juelz_01.0d590b3dd6c58dba054ee00f52a8165966beb310.png"
    },
    {
        "id": "music_kit-65",
        "name": "音樂包 | Knock2 - dashstar*",
        "description": "《dashstar*》是 Knock2 象徵性的低音浩室代表歌曲，充分展現了這位來自聖地牙哥的年輕人的口號——「永無界限」，為大家帶來源源不絕的能量。",
        "rarity": {
            "id": "rarity_rare",
            "name": "高級"
        },
        "exclusive": false,
        "image": "https://steamcdn-a.akamaihd.net/apps/730/icons/econ/music_kits/knock2_01.b7cf197447a161b82c11c8e2d460d510ea58acb4.png"
    },
    {
        "id": "music_kit-66",
        "name": "音樂包 | Meechy Darko - Gothic Luxury",
        "description": "拿起一把格洛克手槍並裝備這個音樂包，瞬間猶如處身紐約充斥地下嘻哈的現場中心。",
        "rarity": {
            "id": "rarity_rare",
            "name": "高級"
        },
        "exclusive": false,
        "image": "https://steamcdn-a.akamaihd.net/apps/730/icons/econ/music_kits/meechydarko_01.5dbe99ff8a2ef9922d84ac61beb9cd685746b886.png"
    },
    {
        "id": "music_kit-67",
        "name": "音樂包 | Sullivan King - Lock Me Up",
        "description": "喜歡追捕與狩獵嗎？Sullivan King 的歌曲中結合了重搖滾、金屬和迴響貝斯，勢不可擋！",
        "rarity": {
            "id": "rarity_rare",
            "name": "高級"
        },
        "exclusive": false,
        "image": "https://steamcdn-a.akamaihd.net/apps/730/icons/econ/music_kits/sullivanking_01.770772c90c1acf349d26cacbbad1a966a825243c.png"
    },
    {
        "id": "music_kit-68",
        "name": "音樂包 | 完美世界 - 花臉",
        "description": "以獨特的花臉音樂包歡慶 CS:GO 於中國推出滿 5 週年。此音樂包混合了民間戲曲「秦腔」（最早期的中國風搖滾）和現代搖滾。不論是被包圍在煙霧之中，還是被閃光彈閃瞎，都不要迷失方向！",
        "rarity": {
            "id": "rarity_rare",
            "name": "高級"
        },
        "exclusive": false,
        "image": "https://steamcdn-a.akamaihd.net/apps/730/icons/econ/music_kits/perfectworld_01.4e4e580548f5d81f30640b2b4cdfa9ba8eec09e0.png"
    },
    {
        "id": "music_kit-69",
        "name": "音樂包 | Denzel Curry - ULTIMATE",
        "description": "Denzel 將他橫跨陷阱音樂、爵士樂、鼓與低音節拍的代表性能量帶到 CS:GO。此音樂包內含 Denzel 的熱門歌曲《Walkin》、《ULTIMATE》，以及更多樂曲。快來「break out nickel-plated chrome Berettas」，用 ULTIMATE 音樂包將熱度再提升！",
        "rarity": {
            "id": "rarity_rare",
            "name": "高級"
        },
        "exclusive": false,
        "image": "https://steamcdn-a.akamaihd.net/apps/730/icons/econ/music_kits/denzelcurry_01.c6308be51b40c63c0addb512fff5d2c9713aceca.png"
    }
]